easygui/__init__.py
easygui/core.py
easygui/demos.py
easygui_win-2.0.0.dist-info/licenses/LICENSE
easygui_win-2.0.0.dist-info/METADATA
easygui_win-2.0.0.dist-info/WHEEL
easygui_win-2.0.0.dist-info/entry_points.txt
easygui_win-2.0.0.dist-info/top_level.txt
easygui_win-2.0.0.dist-info/RECORD
